sonybraviatv_remotecontrol/__init__.py
sonybraviatv_remotecontrol/gateway.py
sonybraviatv_remotecontrol/simpleipprotocol.py
sonybraviatv_remotecontrol-0.3.0.dist-info/LICENSE
sonybraviatv_remotecontrol-0.3.0.dist-info/METADATA
sonybraviatv_remotecontrol-0.3.0.dist-info/WHEEL
sonybraviatv_remotecontrol-0.3.0.dist-info/entry_points.txt
sonybraviatv_remotecontrol-0.3.0.dist-info/top_level.txt
sonybraviatv_remotecontrol-0.3.0.dist-info/RECORD
