Metadata-Version: 2.1
Name: sonybraviatv-remotecontrol
Version: 0.3.0
Summary: Python remote control gateway for sony bravia tv
Home-page: https://github.com/dmachard/sonybraviatv_remotecontrol
Author: Denis MACHARD
Author-email: d.machard@gmail.com
License: UNKNOWN
Keywords: sony bravia tv simple ip remote control
Platform: any
Classifier: License :: OSI Approved :: MIT License
Classifier: Programming Language :: Python :: 3
Classifier: Operating System :: OS Independent
Classifier: Topic :: Software Development :: Libraries
Requires-Dist: websockets
